{
    "total_users": 21,
    "page": 1,
    "pages": 1,
    "pages_list": "1",
    "users": [
        {
            "rank": "Легенда вне Времени",
            "jabber": "",
            "state": "",
            "banrate": 0,
            "last_visit": "2026-01-23 22:35",
            "reg_date": "2025-11-19 17:31",
            "dir_posts": 0,
            "news_posts": 0,
            "email_verified": "no",
            "uID": "no",
            "birthday": "",
            "phone": "",
            "video_posts": 0,
            "options": [
                {
                    "name": "Скрывать email адрес",
                    "code": 1
                },
                {
                    "name": "Принимать письма от других пользователей сайта",
                    "code": 2
                },
                {
                    "name": "Получать почтовые извещения о личных сообщениях",
                    "code": 5
                },
                {
                    "name": "Скрывать телефон",
                    "code": 8
                }
            ],
            "banned": "no",
            "com_posts": 0,
            "signature": "Все готово, можно начинать. Но не забывай... мы следим за тобой.",
            "forum_posts": 3,
            "stuff_posts": 0,
            "yahoo": "",
            "uid": 1,
            "photo_posts": 0,
            "last_visit_timestamp": 1769196929,
            "gender": {
                "name": "Мужской",
                "code": 1
            },
            "title": "Исследователь Вечнос",
            "board_posts": 0,
            "ip": "80.71.157.207",
            "user": "Странник",
            "icq": "",
            "email": "trialportal@inbox.ru",
            "skype": "",
            "avatar": "\/avatar\/00\/00\/00147289.jpg",
            "load_posts": 0,
            "group": {
                "name": "Администратор",
                "id": 4
            },
            "blog_posts": 0,
            "publ_posts": 0,
            "city": "",
            "reg_date_timestamp": 1763562704,
            "home_page": "",
            "country": "",
            "full_name": "Вневременной Странник",
            "status": "offline"
        },
        {
            "signature": "••●☽ Werewolf fangirl ☾●•• <br \/> <a class=\"link\" href=\"https:\/\/discord.gg\/rMrucgTxAg\" rel=\"nofollow\" target=\"_blank\">Мой Discord-сервер<\/a>",
            "com_posts": 0,
            "forum_posts": 6,
            "options": [
                {
                    "name": "Скрывать email адрес",
                    "code": 1
                },
                {
                    "name": "Принимать письма от других пользователей сайта",
                    "code": 2
                },
                {
                    "name": "Получать почтовые извещения о личных сообщениях",
                    "code": 5
                },
                {
                    "code": 8,
                    "name": "Скрывать телефон"
                }
            ],
            "banned": "no",
            "video_posts": 1,
            "phone": "",
            "birthday": "",
            "dir_posts": 0,
            "reg_date": "2025-12-10 21:11",
            "email_verified": "no",
            "uID": "no",
            "news_posts": 1,
            "state": "",
            "jabber": "",
            "banrate": 0,
            "last_visit": "2026-01-21 20:58",
            "rank": "Новобранец",
            "home_page": "https:\/\/worldofwarcraft.blizzard.com\/ru-ru\/character\/eu\/goldrinn\/тентара\/",
            "reg_date_timestamp": 1765390271,
            "full_name": "Тентара",
            "status": "offline",
            "country": "",
            "blog_posts": 0,
            "group": {
                "id": 6,
                "name": "Разработчик"
            },
            "city": "",
            "publ_posts": 13,
            "email": "klabiama@mail.ru",
            "skype": "Тентара-Голдринн",
            "load_posts": 1,
            "avatar": "\/avatar\/00\/00\/00281463.png",
            "ip": "45.15.167.219",
            "board_posts": 0,
            "icq": "",
            "user": "Тентара",
            "gender": {
                "name": "Женский",
                "code": 2
            },
            "title": "",
            "photo_posts": 1,
            "last_visit_timestamp": 1769018338,
            "stuff_posts": 0,
            "yahoo": "",
            "uid": 2
        },
        {
            "ip": "194.180.189.116",
            "board_posts": 0,
            "icq": "",
            "user": "Trumpin",
            "gender": {
                "code": 1,
                "name": "Мужской"
            },
            "title": "",
            "photo_posts": 0,
            "last_visit_timestamp": 1768756941,
            "stuff_posts": 0,
            "yahoo": "",
            "uid": 3,
            "reg_date_timestamp": 1768675230,
            "home_page": "",
            "country": "",
            "status": "offline",
            "full_name": "Трумпин",
            "group": {
                "id": 3,
                "name": "Модератор"
            },
            "blog_posts": 0,
            "publ_posts": 0,
            "city": "",
            "skype": "Трумпин",
            "email": "Step.tru@ya.ru",
            "avatar": "\/avatar\/00\/00\/00331151.png",
            "load_posts": 0,
            "reg_date": "2026-01-17 21:40",
            "dir_posts": 0,
            "news_posts": 0,
            "uID": "no",
            "email_verified": "no",
            "jabber": "",
            "state": "",
            "last_visit": "2026-01-18 20:22",
            "banrate": 0,
            "rank": "Новобранец",
            "com_posts": 0,
            "signature": "",
            "forum_posts": 0,
            "options": [
                {
                    "name": "Скрывать email адрес",
                    "code": 1
                },
                {
                    "name": "Скрывать телефон",
                    "code": 8
                }
            ],
            "banned": "no",
            "phone": "",
            "video_posts": 0,
            "birthday": "2001-05-31"
        },
        {
            "blog_posts": 0,
            "group": {
                "id": 5,
                "name": "Ментор"
            },
            "city": "",
            "publ_posts": 0,
            "skype": "Вразбойник-ВечнаяПесня",
            "email": "r.shadowbreeze@list.ru",
            "load_posts": 0,
            "avatar": "\/avatar\/00\/00\/00472209.png",
            "home_page": "https:\/\/worldofwarcraft.blizzard.com\/ru-ru\/character\/eu\/eversong\/вразбойник",
            "reg_date_timestamp": 1768683925,
            "status": "offline",
            "full_name": "-=V=-",
            "country": "",
            "photo_posts": 0,
            "last_visit_timestamp": 1769179365,
            "stuff_posts": 0,
            "yahoo": "",
            "uid": 4,
            "ip": "185.215.60.104",
            "board_posts": 0,
            "user": "Vrazboynik",
            "icq": "",
            "gender": {
                "code": 1,
                "name": "Мужской"
            },
            "title": "",
            "video_posts": 0,
            "phone": "",
            "birthday": "2008-06-30",
            "signature": "",
            "com_posts": 0,
            "forum_posts": 0,
            "options": [
                {
                    "code": 1,
                    "name": "Скрывать email адрес"
                },
                {
                    "name": "Скрывать телефон",
                    "code": 8
                }
            ],
            "banned": "no",
            "state": "",
            "jabber": "",
            "banrate": 0,
            "last_visit": "2026-01-23 17:42",
            "rank": "Новобранец",
            "dir_posts": 0,
            "reg_date": "2026-01-18 00:05",
            "email_verified": "no",
            "uID": "no",
            "news_posts": 0
        },
        {
            "last_visit_timestamp": 1769191929,
            "photo_posts": 0,
            "uid": 5,
            "yahoo": "",
            "stuff_posts": 0,
            "user": "Reidor",
            "icq": "",
            "ip": "45.15.113.241",
            "board_posts": 0,
            "title": "",
            "gender": {
                "name": "Мужской",
                "code": 1
            },
            "publ_posts": 0,
            "city": "",
            "group": {
                "id": 251,
                "name": "Редактор"
            },
            "blog_posts": 0,
            "avatar": "\/avatar\/00\/00\/00550019.png",
            "load_posts": 0,
            "email": "Reidorr@mail.ru",
            "skype": "Лоренс-ТкачСмерти",
            "country": "",
            "full_name": "Reidor",
            "status": "offline",
            "home_page": "https:\/\/worldofwarcraft.blizzard.com\/ru-ru\/character\/eu\/deathweaver\/лоренс",
            "reg_date_timestamp": 1768686637,
            "last_visit": "2026-01-23 21:12",
            "banrate": 0,
            "jabber": "",
            "state": "",
            "rank": "Новобранец",
            "news_posts": 0,
            "uID": "no",
            "email_verified": "no",
            "reg_date": "2026-01-18 00:50",
            "dir_posts": 0,
            "phone": "",
            "video_posts": 0,
            "birthday": "",
            "forum_posts": 0,
            "signature": "",
            "com_posts": 0,
            "banned": "no",
            "options": [
                {
                    "name": "Скрывать email адрес",
                    "code": 1
                },
                {
                    "code": 8,
                    "name": "Скрывать телефон"
                }
            ]
        },
        {
            "phone": "",
            "video_posts": 0,
            "birthday": "1997-09-09",
            "com_posts": 0,
            "signature": "",
            "forum_posts": 0,
            "options": [
                {
                    "code": 1,
                    "name": "Скрывать email адрес"
                },
                {
                    "code": 8,
                    "name": "Скрывать телефон"
                }
            ],
            "banned": "no",
            "jabber": "",
            "state": "",
            "last_visit": "2026-01-22 23:49",
            "banrate": 0,
            "rank": "Новобранец",
            "reg_date": "2026-01-18 11:30",
            "dir_posts": 0,
            "news_posts": 0,
            "uID": "no",
            "email_verified": "no",
            "group": {
                "name": "Ментор",
                "id": 5
            },
            "blog_posts": 0,
            "publ_posts": 0,
            "city": "",
            "skype": "Амберис-Черный шрам",
            "email": "segan777@mail.ru",
            "avatar": "\/avatar\/00\/00\/00649740.png",
            "load_posts": 0,
            "home_page": "https:\/\/worldofwarcraft.blizzard.com\/ru-ru\/character\/eu\/blackscar\/амберис\/",
            "reg_date_timestamp": 1768725041,
            "country": "",
            "full_name": "Звераго",
            "status": "offline",
            "photo_posts": 0,
            "last_visit_timestamp": 1769114957,
            "yahoo": "",
            "stuff_posts": 0,
            "uid": 6,
            "board_posts": 0,
            "ip": "88.80.63.61",
            "user": "Звераго",
            "icq": "",
            "gender": {
                "name": "Мужской",
                "code": 1
            },
            "title": ""
        },
        {
            "photo_posts": 0,
            "last_visit_timestamp": 1768755072,
            "yahoo": "",
            "stuff_posts": 0,
            "uid": 7,
            "board_posts": 0,
            "ip": "45.94.231.69",
            "user": "DmitriyMorjov",
            "icq": "",
            "gender": {
                "code": 1,
                "name": "Мужской"
            },
            "title": "",
            "group": {
                "id": 255,
                "name": "Заблокированные"
            },
            "blog_posts": 0,
            "publ_posts": 0,
            "city": "",
            "skype": "",
            "email": "terrance.chandler.91@mail.ru",
            "avatar": "",
            "load_posts": 0,
            "home_page": "",
            "reg_date_timestamp": 1768744400,
            "country": "",
            "full_name": "Дмитрий",
            "status": "offline",
            "jabber": "",
            "state": "",
            "banrate": 0,
            "last_visit": "2026-01-18 19:51",
            "rank": "Новобранец",
            "reg_date": "2026-01-18 16:53",
            "dir_posts": 0,
            "news_posts": 0,
            "email_verified": "no",
            "uID": "no",
            "phone": "",
            "video_posts": 0,
            "birthday": "1993-04-08",
            "signature": "",
            "com_posts": 0,
            "forum_posts": 0,
            "options": [
                {
                    "code": 1,
                    "name": "Скрывать email адрес"
                },
                {
                    "code": 8,
                    "name": "Скрывать телефон"
                }
            ],
            "banned": "no"
        },
        {
            "uid": 26,
            "stuff_posts": 0,
            "yahoo": "",
            "last_visit_timestamp": 1768849803,
            "photo_posts": 0,
            "title": "",
            "gender": {
                "name": "Мужской",
                "code": 1
            },
            "user": "TheTraveler1645",
            "icq": "",
            "ip": "178.49.226.16",
            "board_posts": 0,
            "load_posts": 0,
            "avatar": "",
            "email": "trialportal@inbox.ru",
            "skype": "",
            "city": "",
            "publ_posts": 0,
            "blog_posts": 0,
            "group": {
                "id": 1,
                "name": "Новичок"
            },
            "status": "offline",
            "full_name": "",
            "country": "",
            "home_page": "",
            "reg_date_timestamp": 1768742366,
            "rank": "Новобранец",
            "last_visit": "2026-01-19 22:10",
            "banrate": 0,
            "state": "",
            "jabber": "",
            "uID": "no",
            "email_verified": "no",
            "news_posts": 0,
            "dir_posts": 0,
            "reg_date": "2026-01-18 16:19",
            "birthday": "",
            "video_posts": 0,
            "phone": "",
            "banned": "no",
            "options": [
                {
                    "code": 1,
                    "name": "Скрывать email адрес"
                },
                {
                    "code": 2,
                    "name": "Принимать письма от других пользователей сайта"
                },
                {
                    "name": "Получать почтовые извещения о личных сообщениях",
                    "code": 5
                }
            ],
            "forum_posts": 0,
            "signature": "",
            "com_posts": 0
        },
        {
            "phone": "",
            "video_posts": 0,
            "birthday": "2009-02-24",
            "forum_posts": 0,
            "com_posts": 0,
            "signature": "",
            "banned": "no",
            "options": [
                {
                    "code": 1,
                    "name": "Скрывать email адрес"
                },
                {
                    "name": "Скрывать телефон",
                    "code": 8
                }
            ],
            "banrate": 0,
            "last_visit": "2026-01-19 22:34",
            "jabber": "",
            "state": "",
            "rank": "Новобранец",
            "news_posts": 0,
            "uID": "no",
            "email_verified": "no",
            "reg_date": "2026-01-18 20:03",
            "dir_posts": 0,
            "publ_posts": 0,
            "city": "",
            "group": {
                "id": 5,
                "name": "Ментор"
            },
            "blog_posts": 0,
            "avatar": "\/avatar\/00\/00\/01385669.png",
            "load_posts": 0,
            "email": "Devil.Dark.Lord@yandex.ru",
            "skype": "Друидишна-Вечная Песня",
            "country": "",
            "status": "offline",
            "full_name": "Друидишна",
            "home_page": "https:\/\/worldofwarcraft.blizzard.com\/ru-ru\/character\/eu\/eversong\/Друидишна",
            "reg_date_timestamp": 1768755793,
            "last_visit_timestamp": 1768851288,
            "photo_posts": 0,
            "uid": 13,
            "stuff_posts": 0,
            "yahoo": "",
            "user": "Друидишна",
            "icq": "",
            "ip": "46.164.240.188",
            "board_posts": 0,
            "title": "",
            "gender": {
                "code": 1,
                "name": "Мужской"
            }
        },
        {
            "reg_date_timestamp": 1768742366,
            "home_page": "",
            "status": "offline",
            "full_name": "",
            "country": "",
            "blog_posts": 0,
            "group": {
                "id": 1,
                "name": "Новичок"
            },
            "city": "",
            "publ_posts": 0,
            "skype": "",
            "email": "trialportal@inbox.ru",
            "load_posts": 0,
            "avatar": "",
            "board_posts": 0,
            "ip": "178.49.226.16",
            "icq": "",
            "user": "TheTraveler5596",
            "gender": {
                "code": 1,
                "name": "Мужской"
            },
            "title": "",
            "photo_posts": 0,
            "last_visit_timestamp": 1768838692,
            "yahoo": "",
            "stuff_posts": 0,
            "uid": 25,
            "com_posts": 0,
            "signature": "",
            "forum_posts": 0,
            "options": [
                {
                    "code": 1,
                    "name": "Скрывать email адрес"
                },
                {
                    "code": 2,
                    "name": "Принимать письма от других пользователей сайта"
                },
                {
                    "code": 5,
                    "name": "Получать почтовые извещения о личных сообщениях"
                }
            ],
            "banned": "no",
            "video_posts": 0,
            "phone": "",
            "birthday": "",
            "dir_posts": 0,
            "reg_date": "2026-01-18 16:19",
            "uID": "no",
            "email_verified": "no",
            "news_posts": 0,
            "state": "",
            "jabber": "",
            "banrate": 0,
            "last_visit": "2026-01-19 19:04",
            "rank": "Новобранец"
        },
        {
            "rank": "Новобранец",
            "last_visit": "2026-01-23 09:10",
            "banrate": 0,
            "state": "",
            "jabber": "",
            "email_verified": "no",
            "uID": "no",
            "news_posts": 0,
            "dir_posts": 0,
            "reg_date": "2026-01-18 16:19",
            "birthday": "",
            "video_posts": 0,
            "phone": "",
            "banned": "no",
            "options": [
                {
                    "name": "Скрывать email адрес",
                    "code": 1
                },
                {
                    "name": "Принимать письма от других пользователей сайта",
                    "code": 2
                },
                {
                    "code": 5,
                    "name": "Получать почтовые извещения о личных сообщениях"
                }
            ],
            "forum_posts": 0,
            "com_posts": 0,
            "signature": "",
            "uid": 24,
            "yahoo": "",
            "stuff_posts": 0,
            "last_visit_timestamp": 1769148614,
            "photo_posts": 0,
            "title": "",
            "gender": {
                "code": 1,
                "name": "Мужской"
            },
            "user": "TheTraveler",
            "icq": "",
            "board_posts": 0,
            "ip": "178.49.226.16",
            "load_posts": 0,
            "avatar": "",
            "skype": "",
            "email": "trialportal@inbox.ru",
            "city": "",
            "publ_posts": 0,
            "blog_posts": 0,
            "group": {
                "name": "Бот",
                "id": 7
            },
            "full_name": "",
            "status": "offline",
            "country": "",
            "reg_date_timestamp": 1768742366,
            "home_page": ""
        },
        {
            "photo_posts": 0,
            "last_visit_timestamp": 1768938576,
            "stuff_posts": 0,
            "yahoo": "",
            "uid": 27,
            "board_posts": 0,
            "ip": "45.144.31.163",
            "icq": "",
            "user": "Faurnim",
            "gender": {
                "name": "Мужской",
                "code": 1
            },
            "title": "",
            "blog_posts": 0,
            "group": {
                "name": "Новичок",
                "id": 1
            },
            "city": "",
            "publ_posts": 0,
            "email": "frw1999@mail.ru",
            "skype": "Фаурним-Азурегос",
            "load_posts": 0,
            "avatar": "\/avatar\/00\/00\/02716592.jpg",
            "reg_date_timestamp": 1768852026,
            "home_page": "https:\/\/worldofwarcraft.blizzard.com\/ru-ru\/character\/eu\/azuregos\/Фаурним",
            "status": "offline",
            "full_name": "Eduard",
            "country": "",
            "state": "",
            "jabber": "",
            "banrate": 0,
            "last_visit": "2026-01-20 22:49",
            "rank": "Новобранец",
            "dir_posts": 0,
            "reg_date": "2026-01-19 22:47",
            "email_verified": "no",
            "uID": "no",
            "news_posts": 0,
            "video_posts": 0,
            "phone": "",
            "birthday": "1999-02-02",
            "signature": "Триал с 2011 года, но после бана крымских аккаунтов с 2014",
            "com_posts": 0,
            "forum_posts": 0,
            "options": [
                {
                    "name": "Скрывать email адрес",
                    "code": 1
                },
                {
                    "code": 2,
                    "name": "Принимать письма от других пользователей сайта"
                },
                {
                    "name": "Скрывать телефон",
                    "code": 8
                }
            ],
            "banned": "no"
        },
        {
            "banned": "no",
            "options": [
                {
                    "name": "Скрывать email адрес",
                    "code": 1
                },
                {
                    "code": 2,
                    "name": "Принимать письма от других пользователей сайта"
                },
                {
                    "name": "Получать почтовые извещения о личных сообщениях",
                    "code": 5
                }
            ],
            "forum_posts": 0,
            "signature": "",
            "com_posts": 0,
            "birthday": "",
            "phone": "",
            "video_posts": 0,
            "news_posts": 0,
            "email_verified": "no",
            "uID": "no",
            "reg_date": "2026-01-18 16:19",
            "dir_posts": 0,
            "rank": "Новобранец",
            "banrate": 0,
            "last_visit": "2026-01-20 08:07",
            "jabber": "",
            "state": "",
            "country": "",
            "status": "offline",
            "full_name": "",
            "home_page": "",
            "reg_date_timestamp": 1768742366,
            "avatar": "",
            "load_posts": 0,
            "skype": "",
            "email": "trialportal@inbox.ru",
            "publ_posts": 0,
            "city": "",
            "group": {
                "id": 1,
                "name": "Новичок"
            },
            "blog_posts": 0,
            "title": "",
            "gender": {
                "name": "Мужской",
                "code": 1
            },
            "icq": "",
            "user": "TheTraveler2022",
            "ip": "178.49.226.16",
            "board_posts": 0,
            "uid": 28,
            "yahoo": "",
            "stuff_posts": 0,
            "last_visit_timestamp": 1768885654,
            "photo_posts": 0
        },
        {
            "jabber": "",
            "state": "",
            "banrate": 0,
            "last_visit": "2026-01-20 09:30",
            "rank": "Новобранец",
            "reg_date": "2026-01-18 16:19",
            "dir_posts": 0,
            "news_posts": 0,
            "email_verified": "no",
            "uID": "no",
            "phone": "",
            "video_posts": 0,
            "birthday": "",
            "com_posts": 0,
            "signature": "",
            "forum_posts": 0,
            "options": [
                {
                    "code": 1,
                    "name": "Скрывать email адрес"
                },
                {
                    "code": 2,
                    "name": "Принимать письма от других пользователей сайта"
                },
                {
                    "name": "Получать почтовые извещения о личных сообщениях",
                    "code": 5
                }
            ],
            "banned": "no",
            "photo_posts": 0,
            "last_visit_timestamp": 1768890603,
            "stuff_posts": 0,
            "yahoo": "",
            "uid": 29,
            "ip": "178.49.226.16",
            "board_posts": 0,
            "icq": "",
            "user": "TheTraveler4032",
            "gender": {
                "name": "Мужской",
                "code": 1
            },
            "title": "",
            "group": {
                "name": "Новичок",
                "id": 1
            },
            "blog_posts": 0,
            "publ_posts": 0,
            "city": "",
            "email": "trialportal@inbox.ru",
            "skype": "",
            "avatar": "",
            "load_posts": 0,
            "reg_date_timestamp": 1768742366,
            "home_page": "",
            "country": "",
            "full_name": "",
            "status": "offline"
        },
        {
            "last_visit": "2026-01-21 21:04",
            "banrate": 0,
            "state": "",
            "jabber": "",
            "rank": "Новобранец",
            "uID": "no",
            "email_verified": "no",
            "news_posts": 0,
            "dir_posts": 0,
            "reg_date": "2026-01-18 16:19",
            "video_posts": 0,
            "phone": "",
            "birthday": "",
            "forum_posts": 0,
            "com_posts": 0,
            "signature": "",
            "banned": "no",
            "options": [
                {
                    "code": 1,
                    "name": "Скрывать email адрес"
                },
                {
                    "name": "Принимать письма от других пользователей сайта",
                    "code": 2
                },
                {
                    "code": 5,
                    "name": "Получать почтовые извещения о личных сообщениях"
                }
            ],
            "last_visit_timestamp": 1769018694,
            "photo_posts": 0,
            "uid": 30,
            "yahoo": "",
            "stuff_posts": 0,
            "icq": "",
            "user": "TheTraveler3534",
            "board_posts": 0,
            "ip": "178.49.226.16",
            "title": "",
            "gender": {
                "code": 1,
                "name": "Мужской"
            },
            "city": "",
            "publ_posts": 0,
            "blog_posts": 0,
            "group": {
                "name": "Новичок",
                "id": 1
            },
            "load_posts": 0,
            "avatar": "",
            "skype": "",
            "email": "trialportal@inbox.ru",
            "status": "offline",
            "full_name": "",
            "country": "",
            "reg_date_timestamp": 1768742366,
            "home_page": ""
        },
        {
            "rank": "Новобранец",
            "banrate": 0,
            "last_visit": "2026-01-22 09:01",
            "jabber": "",
            "state": "",
            "news_posts": 0,
            "email_verified": "no",
            "uID": "no",
            "reg_date": "2026-01-18 16:19",
            "dir_posts": 0,
            "birthday": "",
            "phone": "",
            "video_posts": 0,
            "banned": "no",
            "options": [
                {
                    "code": 1,
                    "name": "Скрывать email адрес"
                },
                {
                    "code": 2,
                    "name": "Принимать письма от других пользователей сайта"
                },
                {
                    "name": "Получать почтовые извещения о личных сообщениях",
                    "code": 5
                }
            ],
            "forum_posts": 0,
            "com_posts": 0,
            "signature": "",
            "uid": 31,
            "stuff_posts": 0,
            "yahoo": "",
            "last_visit_timestamp": 1769061715,
            "photo_posts": 0,
            "title": "",
            "gender": {
                "code": 1,
                "name": "Мужской"
            },
            "user": "TheTraveler7298",
            "icq": "",
            "ip": "178.49.226.16",
            "board_posts": 0,
            "avatar": "",
            "load_posts": 0,
            "email": "trialportal@inbox.ru",
            "skype": "",
            "publ_posts": 0,
            "city": "",
            "group": {
                "name": "Новичок",
                "id": 1
            },
            "blog_posts": 0,
            "country": "",
            "status": "offline",
            "full_name": "",
            "reg_date_timestamp": 1768742366,
            "home_page": ""
        },
        {
            "gender": {
                "name": "Мужской",
                "code": 1
            },
            "title": "",
            "board_posts": 0,
            "ip": "178.49.226.16",
            "user": "TheTraveler8434",
            "icq": "",
            "stuff_posts": 0,
            "yahoo": "",
            "uid": 32,
            "photo_posts": 0,
            "last_visit_timestamp": 1769103673,
            "reg_date_timestamp": 1768742366,
            "home_page": "",
            "full_name": "",
            "status": "offline",
            "country": "",
            "email": "trialportal@inbox.ru",
            "skype": "",
            "load_posts": 0,
            "avatar": "",
            "blog_posts": 0,
            "group": {
                "id": 1,
                "name": "Новичок"
            },
            "city": "",
            "publ_posts": 0,
            "dir_posts": 0,
            "reg_date": "2026-01-18 16:19",
            "email_verified": "no",
            "uID": "no",
            "news_posts": 0,
            "rank": "Новобранец",
            "state": "",
            "jabber": "",
            "banrate": 0,
            "last_visit": "2026-01-22 20:41",
            "options": [
                {
                    "code": 1,
                    "name": "Скрывать email адрес"
                },
                {
                    "code": 2,
                    "name": "Принимать письма от других пользователей сайта"
                },
                {
                    "code": 5,
                    "name": "Получать почтовые извещения о личных сообщениях"
                }
            ],
            "banned": "no",
            "signature": "",
            "com_posts": 0,
            "forum_posts": 0,
            "birthday": "",
            "video_posts": 0,
            "phone": ""
        },
        {
            "publ_posts": 0,
            "city": "",
            "group": {
                "name": "Новичок",
                "id": 1
            },
            "blog_posts": 0,
            "avatar": "",
            "load_posts": 0,
            "email": "trialportal@inbox.ru",
            "skype": "",
            "country": "",
            "status": "offline",
            "full_name": "",
            "home_page": "",
            "reg_date_timestamp": 1768742366,
            "last_visit_timestamp": 1769148433,
            "photo_posts": 0,
            "uid": 33,
            "stuff_posts": 0,
            "yahoo": "",
            "user": "TheTraveler6414",
            "icq": "",
            "ip": "178.49.226.16",
            "board_posts": 0,
            "title": "",
            "gender": {
                "name": "Мужской",
                "code": 1
            },
            "phone": "",
            "video_posts": 0,
            "birthday": "",
            "forum_posts": 0,
            "com_posts": 0,
            "signature": "",
            "banned": "no",
            "options": [
                {
                    "name": "Скрывать email адрес",
                    "code": 1
                },
                {
                    "name": "Принимать письма от других пользователей сайта",
                    "code": 2
                },
                {
                    "code": 5,
                    "name": "Получать почтовые извещения о личных сообщениях"
                }
            ],
            "last_visit": "2026-01-23 09:07",
            "banrate": 0,
            "jabber": "",
            "state": "",
            "rank": "Новобранец",
            "news_posts": 0,
            "uID": "no",
            "email_verified": "no",
            "reg_date": "2026-01-18 16:19",
            "dir_posts": 0
        },
        {
            "dir_posts": 0,
            "reg_date": "2026-01-18 16:19",
            "uID": "no",
            "email_verified": "no",
            "news_posts": 0,
            "rank": "Новобранец",
            "state": "",
            "jabber": "",
            "banrate": 0,
            "last_visit": "2026-01-23 22:35",
            "options": [
                {
                    "code": 1,
                    "name": "Скрывать email адрес"
                },
                {
                    "name": "Принимать письма от других пользователей сайта",
                    "code": 2
                },
                {
                    "code": 5,
                    "name": "Получать почтовые извещения о личных сообщениях"
                }
            ],
            "banned": "no",
            "com_posts": 0,
            "signature": "",
            "forum_posts": 0,
            "birthday": "",
            "video_posts": 0,
            "phone": "",
            "gender": {
                "name": "Мужской",
                "code": 1
            },
            "title": "",
            "ip": "178.49.226.16",
            "board_posts": 0,
            "icq": "",
            "user": "TheTraveler5758",
            "stuff_posts": 0,
            "yahoo": "",
            "uid": 34,
            "photo_posts": 0,
            "last_visit_timestamp": 1769196939,
            "reg_date_timestamp": 1768742366,
            "home_page": "",
            "full_name": "",
            "status": "offline",
            "country": "",
            "skype": "",
            "email": "trialportal@inbox.ru",
            "load_posts": 0,
            "avatar": "",
            "blog_posts": 0,
            "group": {
                "id": 1,
                "name": "Новичок"
            },
            "city": "",
            "publ_posts": 0
        },
        {
            "email_verified": "no",
            "uID": "no",
            "news_posts": 0,
            "dir_posts": 0,
            "reg_date": "2026-01-23 23:38",
            "rank": "Новобранец",
            "last_visit": "2026-01-23 23:39",
            "banrate": 0,
            "state": "",
            "jabber": "",
            "banned": "no",
            "options": [
                {
                    "name": "Скрывать email адрес",
                    "code": 1
                },
                {
                    "code": 8,
                    "name": "Скрывать телефон"
                }
            ],
            "forum_posts": 0,
            "com_posts": 0,
            "signature": "",
            "birthday": "2003-04-03",
            "video_posts": 0,
            "phone": "",
            "title": "",
            "gender": {
                "name": "Мужской",
                "code": 1
            },
            "icq": "",
            "user": "Sedogriv",
            "ip": "193.168.178.66",
            "board_posts": 0,
            "uid": 35,
            "stuff_posts": 0,
            "yahoo": "",
            "last_visit_timestamp": 1769200777,
            "photo_posts": 0,
            "full_name": "Sedogriv",
            "status": "offline",
            "country": "",
            "reg_date_timestamp": 1769200680,
            "home_page": "https:\/\/worldofwarcraft.blizzard.com\/ru-ru\/character\/eu\/galakrond\/уиггинс\/",
            "load_posts": 0,
            "avatar": "",
            "skype": "Уиггинс-Галакронд",
            "email": "bucenko66@gmail.com",
            "city": "",
            "publ_posts": 0,
            "blog_posts": 0,
            "group": {
                "name": "Новичок",
                "id": 1
            }
        },
        {
            "uid": 36,
            "yahoo": "",
            "stuff_posts": 0,
            "last_visit_timestamp": 0,
            "photo_posts": 0,
            "title": "",
            "gender": {
                "name": "Мужской",
                "code": 1
            },
            "icq": "",
            "user": "TheTraveler3014",
            "board_posts": 0,
            "ip": "178.49.226.16",
            "avatar": "",
            "load_posts": 0,
            "email": "trialportal@inbox.ru",
            "skype": "",
            "publ_posts": 0,
            "city": "",
            "group": {
                "id": 1,
                "name": "Новичок"
            },
            "blog_posts": 0,
            "country": "",
            "status": "tokenOwner",
            "full_name": "",
            "reg_date_timestamp": 1768742366,
            "home_page": "",
            "rank": "Новобранец",
            "banrate": 0,
            "last_visit": "1970-01-01 03:00",
            "jabber": "",
            "state": "",
            "news_posts": 0,
            "email_verified": "yes",
            "uID": "yes",
            "reg_date": "2026-01-18 16:19",
            "dir_posts": 0,
            "birthday": "",
            "phone": "",
            "video_posts": 0,
            "banned": "no",
            "options": [
                {
                    "code": 1,
                    "name": "Скрывать email адрес"
                },
                {
                    "code": 2,
                    "name": "Принимать письма от других пользователей сайта"
                },
                {
                    "code": 5,
                    "name": "Получать почтовые извещения о личных сообщениях"
                }
            ],
            "forum_posts": 0,
            "com_posts": 0,
            "signature": ""
        }
    ],
    "per_page": 50
}